kwaixiaodian-1.0.3.dist-info/METADATA
kwaixiaodian-1.0.3.dist-info/WHEEL
kwaixiaodian-1.0.3.dist-info/entry_points.txt
kwaixiaodian-1.0.3.dist-info/licenses/LICENSE
kwaixiaodian/__init__.py
kwaixiaodian/auth/__init__.py
kwaixiaodian/auth/oauth.py
kwaixiaodian/auth/signature.py
kwaixiaodian/auth/types.py
kwaixiaodian/client/__init__.py
kwaixiaodian/client/base.py
kwaixiaodian/client/main.py
kwaixiaodian/client/oauth.py
kwaixiaodian/client/services/__init__.py
kwaixiaodian/client/services/comment.py
kwaixiaodian/client/services/customer_service.py
kwaixiaodian/client/services/distribution/__init__.py
kwaixiaodian/client/services/distribution/cps.py
kwaixiaodian/client/services/distribution/investment.py
kwaixiaodian/client/services/distribution/main.py
kwaixiaodian/client/services/distribution/second.py
kwaixiaodian/client/services/distribution/seller.py
kwaixiaodian/client/services/dropshipping.py
kwaixiaodian/client/services/funds.py
kwaixiaodian/client/services/industry.py
kwaixiaodian/client/services/invoice.py
kwaixiaodian/client/services/item.py
kwaixiaodian/client/services/live.py
kwaixiaodian/client/services/local_life.py
kwaixiaodian/client/services/logistics.py
kwaixiaodian/client/services/order.py
kwaixiaodian/client/services/photo.py
kwaixiaodian/client/services/promotion.py
kwaixiaodian/client/services/refund.py
kwaixiaodian/client/services/scm.py
kwaixiaodian/client/services/security.py
kwaixiaodian/client/services/service_market.py
kwaixiaodian/client/services/shop.py
kwaixiaodian/client/services/sms.py
kwaixiaodian/client/services/supply.py
kwaixiaodian/client/services/user.py
kwaixiaodian/exceptions.py
kwaixiaodian/http/__init__.py
kwaixiaodian/http/client.py
kwaixiaodian/http/sync_client.py
kwaixiaodian/http/types.py
kwaixiaodian/models/__init__.py
kwaixiaodian/models/base.py
kwaixiaodian/models/comment.py
kwaixiaodian/models/common.py
kwaixiaodian/models/customer_service.py
kwaixiaodian/models/distribution/__init__.py
kwaixiaodian/models/distribution/base.py
kwaixiaodian/models/distribution/cps.py
kwaixiaodian/models/distribution/investment.py
kwaixiaodian/models/distribution/second.py
kwaixiaodian-1.0.3.dist-info/RECORD
