Metadata-Version: 2.1
Name: kwaixiaodian
Version: 1.0.3
Summary: 快手小店开放平台Python SDK - 全功能异步客户端库
Keywords: kuaishou,ecommerce,api,sdk,快手小店
Author-Email: Kuaishou SDK Team <support@kwaixiaodian.com>
License: MIT
Classifier: Development Status :: 5 - Production/Stable
Classifier: Intended Audience :: Developers
Classifier: License :: OSI Approved :: MIT License
Classifier: Programming Language :: Python :: 3
Classifier: Programming Language :: Python :: 3.8
Classifier: Programming Language :: Python :: 3.9
Classifier: Programming Language :: Python :: 3.10
Classifier: Programming Language :: Python :: 3.11
Classifier: Programming Language :: Python :: 3.12
Classifier: Topic :: Internet :: WWW/HTTP
Classifier: Topic :: Software Development :: Libraries :: Python Modules
Classifier: Topic :: Office/Business
Project-URL: Bug Tracker, https://github.com/AndersonBY/kwaixiaodian-python-sdk/issues
Project-URL: Changelog, https://github.com/AndersonBY/kwaixiaodian-python-sdk/blob/main/CHANGELOG.md
Project-URL: Documentation, https://kwaixiaodian-python-sdk.readthedocs.io
Project-URL: Homepage, https://github.com/AndersonBY/kwaixiaodian-python-sdk
Project-URL: Repository, https://github.com/AndersonBY/kwaixiaodian-python-sdk
Requires-Python: >=3.8
Requires-Dist: httpx>=0.25.0
Requires-Dist: pydantic>=2.0.0
Requires-Dist: orjson>=3.8.0
Requires-Dist: cryptography>=41.0.0
Requires-Dist: pendulum>=3.0.0
Requires-Dist: importlib-metadata>=1.0; python_version < "3.8"
Provides-Extra: dev
Requires-Dist: ruff>=0.1.0; extra == "dev"
Requires-Dist: pyright>=1.1.0; extra == "dev"
Requires-Dist: pre-commit>=3.0.0; extra == "dev"
Requires-Dist: types-requests; extra == "dev"
Requires-Dist: build; extra == "dev"
Provides-Extra: docs
Requires-Dist: mkdocs>=1.5.0; extra == "docs"
Requires-Dist: mkdocs-material>=9.0.0; extra == "docs"
Requires-Dist: mkdocstrings[python]>=0.23.0; extra == "docs"
Provides-Extra: test
Requires-Dist: pytest>=7.0.0; extra == "test"
Requires-Dist: pytest-asyncio>=0.21.0; extra == "test"
Requires-Dist: pytest-cov>=4.0.0; extra == "test"
Requires-Dist: pytest-mock>=3.10.0; extra == "test"
Requires-Dist: respx>=0.20.0; extra == "test"
Requires-Dist: httpx>=0.25.0; extra == "test"
